.gitignore
Dockerfile
Jenkinsfile
requirements.txt
setup.py
nmdriver/__init__.py
nmdriver/nmap-driver.py
nmdriver.egg-info/PKG-INFO
nmdriver.egg-info/SOURCES.txt
nmdriver.egg-info/dependency_links.txt
nmdriver.egg-info/requires.txt
nmdriver.egg-info/top_level.txt
nmdriver/config/__init__.py
nmdriver/ipam/__init__.py
nmdriver/ipam/ipam_pb2.py
nmdriver/ipam/ipam_pb2_grpc.py
nmdriver/mgrpc/__init__.py
nmdriver/mgrpc/ipam_pb2.py
nmdriver/mgrpc/ipam_pb2_grpc.py