Metadata-Version: 1.0
Name: nmdriver
Version: 0.0.4
Summary: a library for nmap scan
Home-page: https://192.168.1.146:8081/repo/packages
Author: superman
Author-email: 646390966@qq.com
License: MIT License
Keywords: wx
Platform: any
